{"0": {"charge": 100, "endOfJourney": false, "status": "A-B", "routeID": 0}, "1": {"charge": 100, "endOfJourney": false, "status": "B-A", "routeID": 0}, "2": {"charge": 100, "endOfJourney": false, "status": "A-B", "routeID": 1}, "3": {"charge": 100, "endOfJourney": false, "status": "B-A", "routeID": 1}, "4": {"charge": 100, "endOfJourney": false, "status": "A-B", "routeID": 2}, "5": {"charge": 100, "endOfJourney": false, "status": "B-A", "routeID": 2}, "6": {"charge": 100, "endOfJourney": false, "status": "A-B", "routeID": 3}, "7": {"charge": 100, "endOfJourney": false, "status": "B-A", "routeID": 3}, "8": {"charge": 100, "endOfJourney": false, "status": "A-B", "routeID": 4}, "9": {"charge": 100, "endOfJourney": false, "status": "B-A", "routeID": 4}, "10": {"charge": 100, "endOfJourney": false, "status": "parked", "routeID": null}, "11": {"charge": 100, "endOfJourney": false, "status": "parked", "routeID": null}, "12": {"charge": 100, "endOfJourney": false, "status": "parked", "routeID": null}, "13": {"charge": 100, "endOfJourney": false, "status": "parked", "routeID": null}, "14": {"charge": 100, "endOfJourney": false, "status": "parked", "routeID": null}, "15": {"charge": 100, "endOfJourney": false, "status": "parked", "routeID": null}, "16": {"charge": 100, "endOfJourney": false, "status": "parked", "routeID": null}, "17": {"charge": 100, "endOfJourney": false, "status": "parked", "routeID": null}, "18": {"charge": 100, "endOfJourney": false, "status": "parked", "routeID": null}, "19": {"charge": 100, "endOfJourney": false, "status": "parked", "routeID": null}}